demotools/__init__.py
demotools/command_line.py
demotools/cast/__init__.py
demotools/cast/pointer_cast.py
demo_tools-0.0.3.dist-info/LICENSE
demo_tools-0.0.3.dist-info/METADATA
demo_tools-0.0.3.dist-info/WHEEL
demo_tools-0.0.3.dist-info/entry_points.txt
demo_tools-0.0.3.dist-info/top_level.txt
demo_tools-0.0.3.dist-info/RECORD
