Metadata-Version: 2.1
Name: demo-tools
Version: 0.0.3
Summary: A set of tools which demos for computer learning
Author: mirrordust
License: UNKNOWN
Platform: UNKNOWN
Classifier: Programming Language :: Python :: 3
Classifier: License :: OSI Approved :: MIT License
Classifier: Operating System :: OS Independent
Requires-Python: >=3.6
License-File: LICENSE
